flask_errors_handler/__init__.py
flask_errors_handler/dispatchers.py
flask_errors_handler/exception.py
flask_errors_handler/handler.py
flask_errors_handler/normalize.py
flask_errors_handler/version.py
tests/__init__.py
tests/test_all.py
Flask_ErrorsHandler-4.0.2.dist-info/LICENSE
Flask_ErrorsHandler-4.0.2.dist-info/METADATA
Flask_ErrorsHandler-4.0.2.dist-info/WHEEL
Flask_ErrorsHandler-4.0.2.dist-info/top_level.txt
Flask_ErrorsHandler-4.0.2.dist-info/RECORD
