Metadata-Version: 2.1
Name: Flask-ErrorsHandler
Version: 4.0.2
Summary: Customizable errors handler for flask application and blueprints
Home-page: https://github.com/cs91chris/flask_errors_handler
Author: cs91chris
Author-email: cs91chris@voidbrain.me
License: MIT
Platform: any
Classifier: Environment :: Web Environment
Classifier: Intended Audience :: Developers
Classifier: License :: OSI Approved :: MIT License
Classifier: Operating System :: OS Independent
Classifier: Programming Language :: Python :: 3
Classifier: Topic :: Internet :: WWW/HTTP :: Dynamic Content
Classifier: Topic :: Software Development :: Libraries :: Python Modules
Requires-Dist: Flask (>=1.0.4)
